{
    "id": 1,
    "name": "Nimzowitsch 1...Nc6",
    "course": 1,
    "chapter": 1,
    "alt": false,
    "info": false,
    "moves": "1.e4 Nc6 2.Nf3 d5 3.exd5 Qxd5 4.Nc3 Qh5 5.Nb5",
    "start_move": 2,
    "end_move": 99,
    "data": [
        {
            "move": 1,
            "id": 1,
            "san": "e4",
            "annotation": "",
            "text": "",
            "draw": {}
        },
        {
            "move": 1,
            "id": 2,
            "san": "Nc6",
            "text": "The Nimzovich Defence. It is not that bad if you use it just as a transpositional tool to reach 1 e4 e5 positions - the independent lines, however, are not that reliable for Black, or just downright bad.",
        },
        {
            "move": 2,
            "id": 3,
            "san": "Nf3",
            "text": "Instead, 2.d4 is good as well. But 2.Nf3 is logical and easier to handle.",
        },

    ]
}
